<annotation>
	<folder>images</folder>
	<filename>59e8ea16446f5ee0_jpg.rf.0fc628a9a266a3b8437fccb0783c3059.jpg</filename>
	<path>C:\Users\paris\Desktop\Python\LatteArtCNN\still_human_classsificating\Detecting Coffee and Tea.v1i.yolov5pytorch\train\images\59e8ea16446f5ee0_jpg.rf.0fc628a9a266a3b8437fccb0783c3059.jpg</path>
	<source>
		<database>Unknown</database>
	</source>
	<size>
		<width>640</width>
		<height>640</height>
		<depth>3</depth>
	</size>
	<segmented>0</segmented>
	<object>
		<name>latte</name>
		<pose>Unspecified</pose>
		<truncated>0</truncated>
		<difficult>0</difficult>
		<bndbox>
			<xmin>120</xmin>
			<ymin>239</ymin>
			<xmax>495</xmax>
			<ymax>436</ymax>
		</bndbox>
	</object>
	<object>
		<name>latte</name>
		<pose>Unspecified</pose>
		<truncated>0</truncated>
		<difficult>0</difficult>
		<bndbox>
			<xmin>315</xmin>
			<ymin>117</ymin>
			<xmax>525</xmax>
			<ymax>194</ymax>
		</bndbox>
	</object>
</annotation>
